fnet_flax/__init__.py
fnet_flax/model.py
fnet_flax-0.0.1.dist-info/LICENSE
fnet_flax-0.0.1.dist-info/METADATA
fnet_flax-0.0.1.dist-info/WHEEL
fnet_flax-0.0.1.dist-info/top_level.txt
fnet_flax-0.0.1.dist-info/zip-safe
fnet_flax-0.0.1.dist-info/RECORD
