Metadata-Version: 2.1
Name: fnet-flax
Version: 0.0.1
Summary: Minimal Flax implementation of FNet: Mixing Tokens with Fourier Transforms
Home-page: https://github.com/SauravMaheshkar/FNet-Flax
Author: Saurav Maheshkar
Author-email: sauravvmaheshkar@gmail.com
License: MIT
Platform: UNKNOWN
Requires-Dist: flax
Requires-Dist: jax
